af_worklist_manager/__init__.py
af_worklist_manager/api_client.py
af_worklist_manager/configuration.py
af_worklist_manager/rest.py
af_worklist_manager/api/__init__.py
af_worklist_manager/api/arista_flow_service_api.py
af_worklist_manager/api/default_api.py
af_worklist_manager/api/del_rec_remote_iterator_api.py
af_worklist_manager/api/delegation_manager_api.py
af_worklist_manager/api/inc_admin_worklists_api.py
af_worklist_manager/api/inc_client_worklists_api.py
af_worklist_manager/api/inc_worklist_update_api.py
af_worklist_manager/api/poss_abs_remote_iterator_api.py
af_worklist_manager/api/worklist_administration_api.py
af_worklist_manager/api/worklist_manager_api.py
af_worklist_manager/api/worklist_update_manager_api.py
af_worklist_manager/models/__init__.py
af_worklist_manager/models/abort_service_exception.py
af_worklist_manager/models/abort_transaction_exception.py
af_worklist_manager/models/absence_data.py
af_worklist_manager/models/absence_information.py
af_worklist_manager/models/accessed_process_model_parameter.py
af_worklist_manager/models/activity_agent.py
af_worklist_manager/models/activity_configuration.py
af_worklist_manager/models/activity_reference.py
af_worklist_manager/models/administrative_worklist_item.py
af_worklist_manager/models/af_activity_reference.py
af_worklist_manager/models/af_ebp_reference.py
af_worklist_manager/models/af_instance_reference.py
af_worklist_manager/models/agent_unknown_exception.py
af_worklist_manager/models/assessment.py
af_worklist_manager/models/attribute.py
af_worklist_manager/models/attribute_list.py
af_worklist_manager/models/authentication_exception.py
af_worklist_manager/models/body.py
af_worklist_manager/models/body1.py
af_worklist_manager/models/body2.py
af_worklist_manager/models/client_worklist_callback_data.py
af_worklist_manager/models/client_worklist_item.py
af_worklist_manager/models/client_worklist_item_update.py
af_worklist_manager/models/client_worklist_rest_callback_data.py
af_worklist_manager-4.0.3.dist-info/LICENSE
af_worklist_manager-4.0.3.dist-info/METADATA
af_worklist_manager-4.0.3.dist-info/WHEEL
af_worklist_manager-4.0.3.dist-info/top_level.txt
af_worklist_manager-4.0.3.dist-info/RECORD
